decision_footnote/__init__.py
decision_footnote/make.py
decision_footnote/validate.py
decision_footnote-0.0.1.dist-info/WHEEL
decision_footnote-0.0.1.dist-info/METADATA
decision_footnote-0.0.1.dist-info/RECORD
