Metadata-Version: 2.1
Name: decision-footnote
Version: 0.0.1
Summary: Split html style sup-footnotes to validated list of dicts
Author: Marcelino G. Veloso III
Author-email: mars@veloso.one
Requires-Python: >=3.9,<4.0
Classifier: Programming Language :: Python :: 3
Classifier: Programming Language :: Python :: 3.9
Classifier: Programming Language :: Python :: 3.10
Requires-Dist: lawsql-utils (>=0.0.1,<0.0.2)
